compytition/__init__.py
compytition/outcome.py
compytition/outcome_to_points_mapping.py
compytition/rank.py
compytition/rank_list.py
compytition/ranking.py
compytition-0.3.1.dist-info/METADATA
compytition-0.3.1.dist-info/WHEEL
compytition-0.3.1.dist-info/RECORD
