Metadata-Version: 2.1
Name: compytition
Version: 0.3.1
Summary: A library for all sorts of ranking, rating and scoring classes and algorithms
License: GPL-3.0-only
Author: peaky76
Author-email: robertjamespeacock@gmail.com
Requires-Python: >=3.11,<4.0
Classifier: License :: OSI Approved :: GNU General Public License v3 (GPLv3)
Classifier: Programming Language :: Python :: 3
Classifier: Programming Language :: Python :: 3.11
Requires-Dist: peak-utility (>=0.6,<0.8)
